{
  "version": 5,
  "name": "formula_1_playdate.zip",
  "items": [
    "Formula 1 Playdate.sh",
    "formula_1_playdate/"
  ],
  "items_opt": [],
  "attr": {
    "title": "Formula 1 Playdate",
    "porter": [
      "Joyrider3774"
    ],
    "desc": "Formula 1 Playdate is the Playdate version of a small, fictive game and watch style lcd game with high score keeping. The aim of the game is to avoid hitting other traffic coming down the screen, by moving your car on the bottom left or right.",
    "desc_md": null,
    "inst": "Ready to run.",
    "inst_md": null,
    "genres": [
      "arcade",
      "racing"
    ],
    "image": null,
    "rtr": true,
    "exp": false,
    "runtime": null,
    "reqs": [],
    "arch": [
      "aarch64",
      "armhf"
    ],
    "availability": "full",
    "free": true,
    "itchio_url": "https://joyrider3774.itch.io/forumla-1-game-watch-playdate"
  }
}