{
  "version": 4,
  "name": "sawa.zip",
  "items": [
    "Super Amazing Wagon Adventure.sh",
    "sawa"
  ],
  "items_opt": [],
  "attr": {
    "title": "Super Amazing Wagon Adventure",
    "porter": [
      "JanTrueno"
    ],
    "desc": "Super Amazing Wagon Adventure is a fast-paced 2d shooting game with a random story. You control a group of three migrants traveling west along a wagon trail. The game consists of short scenes that are sequenced together in a semi-random way to tell a crazy adventure story.",
    "desc_md": null,
    "inst": "Install portfiles with PM autoinstaller. Buy and install Super Amazing Wagon Adventure. Copy all files to  the \"sawa/gamedata\" folder.",
    "inst_md": "- Install portfiles with PM autoinstaller.\n- Buy and install [Super Amazing Wagon Adventure](https://store.steampowered.com/app/250500/Super_Amazing_Wagon_Adventure/).\n- Copy all files to  the \"sawa/gamedata\" folder.",
    "genres": [
      "action",
      "adventure"
    ],
    "image": null,
    "rtr": false,
    "exp": false,
    "runtime": ["mono-6.12.0.122-aarch64.squashfs"],
    "store": [
      {
        "name": "Steam",
        "url": "https://store.steampowered.com/app/250500/Super_Amazing_Wagon_Adventure/"
      }
    ],
    "availability": "paid",
    "reqs": [],
    "arch": [],
    "min_glibc": "",
    "steam_id": 250500,
    "igdb_id": 13100
  }
}