{
    "version": 2,
    "name": "srb2kart.zip",
    "items": [
        "Sonic Robo Blast 2 Kart.sh",
        "srb2kart/"
    ],
    "items_opt": null,
    "attr": {
        "title": "Sonic RB2 Kart",
        "desc": "Sonic Robo Blast 2 Kart fangame by Sonic Team Junior.  All necessary files are already included.  !!!Warning!!! This is a 184MB package and will take a while to download and install.",
        "inst": "Ready to run.",
        "genres": [
            "racing"
        ],
        "porter": [
            "romadu"
        ],
        "image": {},
        "rtr": true,
        "runtime": null,
        "reqs": [],
        "arch": [
            "aarch64"
        ]
    }
}