{
  "version": 2,
  "name": "ioawn4t.zip",
  "items": [
    "If On A Winter's Night, Four Travelers.sh",
    "ioawn4t"
  ],
  "items_opt": [],
  "attr": {
    "title": "If On A Winter's Night, Four Travelers",
    "porter": [
      "JanTrueno"
    ],
    "desc": "If On A Winter's Night, Four Travelers is a free narrative-driven point-and-click adventure that explores the stories of four different characters in a masked ball taking place on a train in the late 1920s.",
    "inst": "Download the windows version of the game on Itch or Steam. Copy all assets, including the executable, into the gamedata folder.",
    "genres": [
      "adventure"
    ],
    "image": null,
    "rtr": false,
    "exp": false,
    "runtime": null,
    "reqs": [],
    "arch": [
      "aarch64"
    ]
  }
}
