{
  "version": 4,
  "name": "revbros.zip",
  "items": [
    "Reverse Bros.sh",
    "revbros/"
  ],
  "items_opt": [],
  "attr": {
    "title": "Reverse Bros",
    "porter": [
      "MadShmupper"
    ],
    "desc": "Make way for both characters reach the prize\n\nRULES\nWhite character only walks on black tiles and vice versa;\nWhite character turns black tiles into whites and vice versa;",
    "desc_md": "## Objective\nMake way for both characters to reach the prize.\n\n## Rules\n- White character only walks on black tiles and vice versa\n- White character turns black tiles into whites and vice versa",
    "inst": "Ready to Run",
    "inst_md": null,
    "genres": [
      "puzzle"
    ],
    "image": null,
    "rtr": true,
    "exp": false,
    "runtime": null,
    "store": null,
    "availability": "full",
    "reqs": [],
    "arch": [
      "armhf"
    ],
    "itchio_url": "https://all-x.itch.io/reverse-bros"
  }
}