{
  "version": 4,
  "name": "bunnysflowers.zip",
  "items": [
    "Bunny's Flowers.sh",
    "bunnysflowers"
  ],
  "items_opt": [],
  "attr": {
    "title": "Bunny's Flowers",
    "porter": [
      "Kompaan"
    ],
    "desc": "Bunny’s Flowers is a cute, wholesome puzzle game about taking a trip to your grandma's house. Overcome box-pushing challenges using your mysterious magical power.",
    "desc_md": null,
    "inst": "Purchase game on steam. Copy data.win, audiogroup1.dat  and audiogroup2.dat files into the /ports/bunnysflowers/gamedata directory",
    "inst_md": null,
    "genres": [
      "puzzle"
    ],
    "image": "screenshot.png",
    "rtr": false,
    "exp": false,
    "runtime": null,
    "store": [
      {
        "name": "steam",
        "gameurl": "https://store.steampowered.com/app/1375480"
      }
    ],
    "availability": "paid",
    "reqs": [],
    "arch": [
      "armhf"
    ],
    "min_glibc": ""
  }
}