{
  "version": 3,
  "name": "digitaltamersreborn.zip",
  "items": [
    "DigitalTamers Reborn.sh",
    "digitamersreborn"
  ],
  "items_opt": [],
  "attr": {
    "title": "DigitalTamers Reborn",
    "porter": [
      "Jeod"
    ],
    "desc": "Train, fight, evolve! Digital Tamers: ReBorn is a casual fighting game for all Digimon fans. Your mission is to take care of your partner, keep it strong, healthy in order to evolve and win battles and several prizes! Excel and win the 12 Championships that will take place throughout the year in order to become a true Digimon Tamer! Live this experience and welcome, to the Digital World!",
    "inst": "Download the Windows executable from https://dragonrod342.itch.io/digital-tamers-reborn and put in the `ports/digitamersreborn/assets` folder..",
    "inst_md": null,
    "genres": [
      "action"
    ],
    "image": null,
    "rtr": false,
    "exp": false,
    "runtime": null,
    "reqs": ["analog_1|analog_2"],
    "arch": [
      "armhf"
    ]
  }
}