{
  "version": 4,
  "name": "hyperoverlap2.zip",
  "items": [
    "Hyper Overlap 2 - Turbo Edition.sh",
    "hyperoverlap2"
  ],
  "items_opt": [],
  "attr": {
    "title": "Hyper Overlap 2: Turbo Edition",
    "porter": [
      "Ganimoth"
    ],
    "desc": "In the future year of 199X, the world was finally united in 7 grand cartridges. But one day, the [Glitch Wizard] decided to take it one step further! Play every game at once (not in a good way!) as you fight against the glitches and corruption.",
    "desc_md": null,
    "inst": "Download the game from Itch.io and extract all files into the assets folder.",
    "inst_md": "Download the game from [Itch.io](https://yaru.itch.io/hyper-overlap-2-turbo-edition) and extract all files into the `assets` folder.",
    "genres": [
      "arcade"
    ],
    "image": null,
    "rtr": false,
    "exp": false,
    "runtime": [],
    "store": [
      {
        "name": "Itch.io",
        "gameurl": "https://yaru.itch.io/hyper-overlap-2-turbo-edition",
        "developerurl": ""
      }
    ],
    "availability": "free",
    "reqs": [],
    "arch": [
      "aarch64"
    ],
    "min_glibc": ""
  }
}