<?xml version="1.0"?>
<particles emitter="point">

    <spreading angle="30"        />
    
    <velocity  x="0.0"
               y="0.003"
               z="0.0"           />
    
    <material  file="smoke.png"  />
    
    <!-- Amount of particles emitted per second -->
    <rate      min="70"
               max="80"          />
    
    <!-- Minimal and maximal lifetime of a particle, in milliseconds. -->
    <lifetime  min="2000"
               max="4000"        />
    
    <!-- Size of the particles -->
    <size      min="1.6"
               max="2.5"
               x-increase-factor="2.6"
               y-increase-factor="2.6"         />

    <color     min="35 35 35"
               max="100 100 100" />

    <!-- How much time in milliseconds before the particle is fully faded out  -->
    <fadeout   time="2000"       />

</particles>
