<?xml version="1.0" encoding="utf-8"?>
<gameList>
  <game>
    <path>./Doom RPG.sh</path>
    <name>Doom RPG</name>
    <desc>Doom RPG is a mobile phone game developed by Fountainhead Entertainment . It combines the Doom first-person shooter franchise with role-playing video game elements. The storyline incorporates many similar events of Doom 3, but involves different characters than those in the third game.</desc>
    <releasedate>20050919T000000</releasedate>
    <developer>Fountainhead Entertainment</developer>
    <publisher>JAMDAT Mobile</publisher>
    <genre>RPG</genre>
    <image>./doomrpg/screenshot.png</image>
  </game>
</gameList>