<?xml version="1.0" encoding="utf-8"?>
<gameList>
  <game>
    <path>./SPROUT.sh</path>
    <name>-SPROUT-</name>
    <desc>-SPROUT- is a mini precision-platformer built for speed-running. Run, jump and dash your way through 100 levels across five unique lands, and restore your world to its former glory</desc>
    <releasedate>20200730T000000</releasedate>
    <developer>Zedsquadron</developer>
    <publisher>Sparkee Software, LLC</publisher>
    <genre>Platformer</genre>
    <image>./sprout/cover.png</image>
  </game>
</gameList>