{
    "version": 5,
    "name": "thelegendoflumina.zip",
    "items": [
        "The Legend of Lumina",
        "thelegendoflumina"
    ],
    "items_opt": [],
    "attr": {
        "title": "The Legend Of Lumina",
        "porter": [
            "JanTrueno",
            "Kompaan"
        ],
        "desc": "Explore an ancient forest, push blocks to solve puzzles, and search for a way to end the curse on your land.",
        "desc_md": null,
        "inst": "You can download the game for free on itch:\nhttps://wizbane.itch.io/the-legend-of-lumina\n\nGrab the linux .pck and install in the gamedata folder. ",
        "inst_md": null,
        "genres": [
            "puzzle",
            "adventure"
        ],
        "image": null,
        "rtr": false,
        "exp": false,
        "runtime": ["frt_3.5.2.squashfs"],
        "store": [
            {
                "name": "Steam",
                "url": "https://store.steampowered.com/app/2638340/"
            },
            {
                "name": "itch.io",
                "url": "https://wizbane.itch.io/the-legend-of-lumina"
            }
        ],
        "availability": "free",
        "reqs": [],
        "arch": [],
        "min_glibc": "",
        "steam_id": 2638340,
        "itchio_url": "https://wizbane.itch.io/the-legend-of-lumina"
    }
}