{
    "version": 3,
    "name": "demonofsakurapass.zip",
    "items": [
        "Demon of Sakura Pass.sh",
        "demonofsakurapass"
    ],
    "items_opt": null,
    "attr": {
        "title": "Demon of Sakura Pass",
        "porter": [
            "tabreturn"
        ],
        "desc": "A brutal single-player racing game with simplified driving mechanics that reward a good racing line and savagely punish bad technique. Focus on learning each track's unique challenges to overcome each racer and move on to the next. Unwrap the mystery haunting Sakura Pass in a 7-stage campaign.",
        "desc_md": null,
        "inst": "Purchase the game on itch.io (https://brainos.itch.io/touge), download the The Demon of Sakura Pass.exe version and copy it to the port's gamedata folder.",
        "inst_md": "Purchase the game on [itch.io](https://brainos.itch.io/touge), download the *The Demon of Sakura Pass.exe* version and copy it to the port's *gamedata* folder.",
        "genres": [
            "racing"
        ],
        "image": {},
        "rtr": false,
        "exp": false,
        "runtime": null,
        "reqs": [],
        "arch": [
            "armhf"
        ]
    }
}