{
	"map" : 
	{
		"center" : [ 743.1896, 87.99147, 709.3239 ],
		"dialogs" : 
		[
			{
				"participant" : 
				[
					{
						"pos" : [ 1037.414, 84.73706, 805.8795 ],
						"yaw" : 91.00001
					},
					{
						"pos" : [ 1040.252, 85.11043, 805.9663 ],
						"yaw" : -1900.486
					},
					{
						"pos" : [ 0.0, 0.0, 0.0 ],
						"yaw" : 0.0
					},
					{
						"pos" : [ 0.0, 0.0, 0.0 ],
						"yaw" : 0.0
					},
					{
						"pos" : [ 0.0, 0.0, 0.0 ],
						"yaw" : 0.0
					},
					{
						"pos" : [ 0.0, 0.0, 0.0 ],
						"yaw" : 0.0
					},
					{
						"pos" : [ 0.0, 0.0, 0.0 ],
						"yaw" : 0.0
					},
					{
						"pos" : [ 0.0, 0.0, 0.0 ],
						"yaw" : 0.0
					},
					{
						"pos" : [ 0.0, 0.0, 0.0 ],
						"yaw" : 0.0
					},
					{
						"pos" : [ 0.0, 0.0, 0.0 ],
						"yaw" : 0.0
					}
				],
				"scenes" : 
				[
					{
						"camera" : 
						{
							"pitch" : -0.3000153,
							"pos" : [ 1036.937, 86.4678, 805.3522 ],
							"yaw" : 105.1
						},
						"color" : [ 0.0, 0.0, 0.0 ],
						"location" : 1,
						"name" : " Turner",
						"participantaction" : 0,
						"participantfacing" : 
						[
							[ 0.9982044, 0.0574661, -0.01690526 ],
							[ -0.979392, -0.0892236, -0.1811929 ],
							[ -0.8745372, -0.1398523, 0.4643555 ],
							[ -0.1649997, -0.7674707, -0.6194867 ],
							[ -0.00418721, -0.1154975, -0.9932991 ],
							[ 0.9961234, -0.07435289, -0.04701114 ],
							[ 0.0, 0.0, 0.0 ],
							[ 0.0, 0.0, 0.0 ],
							[ 0.0, 0.0, 0.0 ],
							[ 0.0, 0.0, 0.0 ]
						],
						"participantfocus" : 0,
						"sound" : 6,
						"text" : "Where's Shan? I must speak with him."
					},
					{
						"camera" : 
						{
							"pitch" : 16.49998,
							"pos" : [ 1038.791, 86.5955, 805.5604 ],
							"yaw" : 105.1
						},
						"color" : [ 0.1, 0.2, 0.0 ],
						"location" : 2,
						"name" : " Ray",
						"participantaction" : 0,
						"participantfacing" : 
						[
							[ 0.9982044, 0.0574661, -0.01690526 ],
							[ -0.979392, -0.0892236, -0.1811929 ],
							[ -0.8745372, -0.1398523, 0.4643555 ],
							[ -0.1649997, -0.7674707, -0.6194867 ],
							[ -0.00418721, -0.1154975, -0.9932991 ],
							[ 0.9961234, -0.07435289, -0.04701114 ],
							[ 0.0, 0.0, 0.0 ],
							[ 0.0, 0.0, 0.0 ],
							[ 0.0, 0.0, 0.0 ],
							[ 0.0, 0.0, 0.0 ]
						],
						"participantfocus" : 1,
						"sound" : 1,
						"text" : "Already gone. I don't know where, I'm not from his\rclan."
					}
				],
				"type" : 11
			},
			{
				"participant" : 
				[
					{
						"pos" : [ 1061.701, 85.51454, 807.6097 ],
						"yaw" : 443.1999
					},
					{
						"pos" : [ 1040.252, 85.11043, 805.9663 ],
						"yaw" : -1900.486
					},
					{
						"pos" : [ 1064.16, 85.57176, 807.6967 ],
						"yaw" : 2457.988
					},
					{
						"pos" : [ 0.0, 0.0, 0.0 ],
						"yaw" : 0.0
					},
					{
						"pos" : [ 0.0, 0.0, 0.0 ],
						"yaw" : 0.0
					},
					{
						"pos" : [ 0.0, 0.0, 0.0 ],
						"yaw" : 0.0
					},
					{
						"pos" : [ 0.0, 0.0, 0.0 ],
						"yaw" : 0.0
					},
					{
						"pos" : [ 0.0, 0.0, 0.0 ],
						"yaw" : 0.0
					},
					{
						"pos" : [ 0.0, 0.0, 0.0 ],
						"yaw" : 0.0
					},
					{
						"pos" : [ 0.0, 0.0, 0.0 ],
						"yaw" : 0.0
					}
				],
				"scenes" : 
				[
					{
						"camera" : 
						{
							"pitch" : 0.6999832,
							"pos" : [ 1062.755, 87.28536, 807.9147 ],
							"yaw" : -433.9995
						},
						"color" : [ 0.0, 0.0, 0.2 ],
						"location" : 1,
						"name" : " Skipper",
						"participantaction" : 0,
						"participantfacing" : 
						[
							[ 0.9925466, -0.02539022, 0.1191929 ],
							[ -0.9820902, -0.04537889, -0.1828661 ],
							[ -0.9777055, -0.08541669, -0.1918225 ],
							[ -0.1649997, -0.7674707, -0.6194867 ],
							[ -0.00418721, -0.1154975, -0.9932991 ],
							[ 0.9961234, -0.07435289, -0.04701114 ],
							[ 0.868813, -0.4950866, -0.007316724 ],
							[ 0.0, 0.0, 0.0 ],
							[ 0.0, 0.0, 0.0 ],
							[ 0.0, 0.0, 0.0 ]
						],
						"participantfocus" : 0,
						"sound" : 6,
						"text" : "Where did Shan go?"
					},
					{
						"camera" : 
						{
							"pitch" : 36.39999,
							"pos" : [ 1065.377, 87.93922, 808.4708 ],
							"yaw" : -435.3998
						},
						"color" : [ 0.0, 0.0, 0.0 ],
						"location" : 1,
						"name" : " Turner",
						"participantaction" : 0,
						"participantfacing" : 
						[
							[ 0.9925466, -0.02539022, 0.1191929 ],
							[ -0.9820902, -0.04537889, -0.1828661 ],
							[ -0.9777055, -0.08541669, -0.1918225 ],
							[ -0.1649997, -0.7674707, -0.6194867 ],
							[ -0.00418721, -0.1154975, -0.9932991 ],
							[ 0.9961234, -0.07435289, -0.04701114 ],
							[ 0.868813, -0.4950866, -0.007316724 ],
							[ 0.0, 0.0, 0.0 ],
							[ 0.0, 0.0, 0.0 ],
							[ 0.0, 0.0, 0.0 ]
						],
						"participantfocus" : 2,
						"sound" : 3,
						"text" : "..."
					},
					{
						"camera" : 
						{
							"pitch" : 4.89999,
							"pos" : [ 1062.928, 87.47552, 808.7365 ],
							"yaw" : -396.9005
						},
						"color" : [ 0.0, 0.0, 0.2 ],
						"location" : 1,
						"name" : " Skipper",
						"participantaction" : 0,
						"participantfacing" : 
						[
							[ -0.4521521, 0.1218695, -0.8835759 ],
							[ -0.9820902, -0.04537889, -0.1828661 ],
							[ -0.9777055, -0.08541669, -0.1918225 ],
							[ -0.1649997, -0.7674707, -0.6194867 ],
							[ -0.00418721, -0.1154975, -0.9932991 ],
							[ 0.9961234, -0.07435289, -0.04701114 ],
							[ 0.868813, -0.4950866, -0.007316724 ],
							[ 0.0, 0.0, 0.0 ],
							[ 0.0, 0.0, 0.0 ],
							[ 0.0, 0.0, 0.0 ]
						],
						"participantfocus" : 0,
						"sound" : 1,
						"text" : "I've been attacked by water clan men. I must speak\rwith him."
					},
					{
						"camera" : 
						{
							"pitch" : 4.899991,
							"pos" : [ 1062.638, 86.62224, 808.2355 ],
							"yaw" : -298.9004
						},
						"color" : [ 0.0, 0.0, 0.2 ],
						"location" : 2,
						"name" : " Skipper",
						"participantaction" : 0,
						"participantfacing" : 
						[
							[ -0.4521521, 0.1218695, -0.8835759 ],
							[ -0.9820902, -0.04537889, -0.1828661 ],
							[ -0.2503132, -0.6959128, 0.6730889 ],
							[ 0.0, 0.0, 0.0 ],
							[ 0.0, 0.0, 0.0 ],
							[ 0.0, 0.0, 0.0 ],
							[ 0.0, 0.0, 0.0 ],
							[ 0.0, 0.0, 0.0 ],
							[ 0.0, 0.0, 0.0 ],
							[ 0.0, 0.0, 0.0 ]
						],
						"participantfocus" : 2,
						"sound" : 1,
						"text" : "...He's been called back to our fort. Something\rmust have happened."
					},
					{
						"camera" : 
						{
							"pitch" : 36.39999,
							"pos" : [ 1065.377, 87.93922, 808.4708 ],
							"yaw" : -435.3998
						},
						"color" : [ 0.0, 0.0, 0.0 ],
						"location" : 1,
						"name" : " Turner",
						"participantaction" : 0,
						"participantfacing" : 
						[
							[ 0.9925466, -0.02539022, 0.1191929 ],
							[ -0.9820902, -0.04537889, -0.1828661 ],
							[ -0.9777055, -0.08541669, -0.1918225 ],
							[ -0.1649997, -0.7674707, -0.6194867 ],
							[ -0.00418721, -0.1154975, -0.9932991 ],
							[ 0.9961234, -0.07435289, -0.04701114 ],
							[ 0.868813, -0.4950866, -0.007316724 ],
							[ 0.0, 0.0, 0.0 ],
							[ 0.0, 0.0, 0.0 ],
							[ 0.0, 0.0, 0.0 ]
						],
						"participantfocus" : 2,
						"sound" : 4,
						"text" : "He's handled the raiders all right, though. You\rcould watch the bodies rain from the sky."
					},
					{
						"camera" : 
						{
							"pitch" : 2.799993,
							"pos" : [ 1063.149, 87.35761, 807.6004 ],
							"yaw" : -464.8005
						},
						"color" : [ 0.0, 0.0, 0.2 ],
						"location" : 2,
						"name" : " Skipper",
						"participantaction" : 0,
						"participantfacing" : 
						[
							[ -0.855756, 0.07323832, 0.5121697 ],
							[ -0.9820902, -0.04537889, -0.1828661 ],
							[ -0.2503132, -0.6959128, 0.6730889 ],
							[ 0.0, 0.0, 0.0 ],
							[ 0.0, 0.0, 0.0 ],
							[ 0.0, 0.0, 0.0 ],
							[ 0.0, 0.0, 0.0 ],
							[ 0.0, 0.0, 0.0 ],
							[ 0.0, 0.0, 0.0 ],
							[ 0.0, 0.0, 0.0 ]
						],
						"participantfocus" : 0,
						"sound" : 1,
						"text" : "I have to go to your fort. It's probably under\rattack from the water clan."
					},
					{
						"camera" : 
						{
							"pitch" : 23.09999,
							"pos" : [ 1065.504, 87.48701, 808.7205 ],
							"yaw" : -423.4997
						},
						"color" : [ 0.0, 0.0, 0.0 ],
						"location" : 1,
						"name" : " Turner",
						"participantaction" : 0,
						"participantfacing" : 
						[
							[ 0.9925466, -0.02539022, 0.1191929 ],
							[ -0.9820902, -0.04537889, -0.1828661 ],
							[ -0.9777055, -0.08541669, -0.1918225 ],
							[ -0.1649997, -0.7674707, -0.6194867 ],
							[ -0.00418721, -0.1154975, -0.9932991 ],
							[ 0.9961234, -0.07435289, -0.04701114 ],
							[ 0.868813, -0.4950866, -0.007316724 ],
							[ 0.0, 0.0, 0.0 ],
							[ 0.0, 0.0, 0.0 ],
							[ 0.0, 0.0, 0.0 ]
						],
						"participantfocus" : 2,
						"sound" : 6,
						"text" : "If there is something our fort can't handle, you'd\rbetter be stealthy in your approach."
					}
				],
				"type" : 32
			}
		],
		"environment" : 2,
		"fadestart" : 0.6,
		"hostile" : 1,
		"objects" : 
		[
			[
				6,
				0.0,
				0.0,
				0.1,
				[ 1094.028, 82.57748, 812.6294 ]
			],
			[
				11,
				0.0,
				0.0,
				0.7614588,
				[ 1094.645, -319.0436, 812.642 ]
			],
			[
				9,
				0.0,
				0.0,
				1.699979,
				[ 1094.999, 186.2249, 758.5963 ]
			],
			[
				9,
				0.0,
				0.0,
				1.699979,
				[ 1095.992, -313.908, 711.9006 ]
			],
			[
				9,
				0.0,
				0.0,
				1.699979,
				[ 1095.992, -313.8698, 711.9006 ]
			],
			[
				9,
				0.0,
				0.0,
				1.699979,
				[ 1094.507, -313.8199, 865.4426 ]
			],
			[
				9,
				0.0,
				0.0,
				1.699979,
				[ 1095.826, -312.7458, 709.2507 ]
			],
			[
				9,
				0.0,
				0.0,
				1.699979,
				[ 1095.826, 186.2007, 709.2507 ]
			],
			[
				7,
				0.0,
				0.0,
				0.6190739,
				[ 1111.042, -316.5314, 865.1857 ]
			],
			[
				7,
				0.0,
				0.0,
				0.6190739,
				[ 1077.669, -317.1141, 864.6569 ]
			],
			[
				11,
				90.0,
				0.0,
				0.267418,
				[ 1094.116, -299.4389, 864.7665 ]
			],
			[
				9,
				90.0,
				0.0,
				1.784242,
				[ 1093.505, -293.8505, 889.022 ]
			],
			[
				7,
				0.0,
				0.0,
				1.784242,
				[ 1097.191, -316.7657, 889.6851 ]
			],
			[
				8,
				0.0,
				0.0,
				0.6464519,
				[ 1079.512, -279.1509, 880.1468 ]
			],
			[
				8,
				0.0,
				0.0,
				0.6464519,
				[ 1112.737, -278.7023, 880.7507 ]
			],
			[
				11,
				90.0,
				0.0,
				0.6464519,
				[ 1095.061, -266.514, 880.1883 ]
			],
			[
				3,
				90.0,
				0.0,
				0.9142139,
				[ 1102.057, -265.0514, 880.2307 ]
			],
			[
				3,
				90.0,
				0.0,
				0.9142139,
				[ 1090.506, -265.0659, 880.8587 ]
			],
			[
				3,
				90.0,
				0.0,
				1.955105,
				[ 1090.556, -265.0108, 877.7029 ]
			],
			[
				3,
				90.0,
				0.0,
				1.955105,
				[ 1102.129, -265.0008, 877.3322 ]
			],
			[
				12,
				0.0,
				90.0,
				0.3440635,
				[ 1096.601, -245.5422, 877.0659 ]
			],
			[
				8,
				0.0,
				180.0,
				0.150808,
				[ 1087.933, -312.8972, 780.9299 ]
			],
			[
				8,
				0.0,
				180.0,
				0.150808,
				[ 1102.413, -312.6443, 781.5752 ]
			],
			[
				9,
				0.0,
				180.0,
				0.1,
				[ 1088.047, -309.7507, 780.9849 ]
			],
			[
				9,
				0.0,
				180.0,
				0.1,
				[ 1102.501, -309.5022, 781.723 ]
			],
			[
				11,
				90.0,
				68.0,
				0.4983349,
				[ 1114.78, -316.4248, 775.3347 ]
			],
			[
				11,
				270.0,
				68.0,
				0.4983349,
				[ 1076.5, -317.093, 775.1819 ]
			],
			[
				8,
				270.0,
				0.0,
				0.1591308,
				[ 1087.99, -312.1879, 780.2853 ]
			],
			[
				8,
				270.0,
				0.0,
				0.1591308,
				[ 1103.03, -313.0838, 781.0887 ]
			],
			[
				8,
				270.0,
				0.0,
				0.1591308,
				[ 1087.649, -313.2362, 781.0033 ]
			],
			[
				9,
				270.0,
				0.0,
				0.1,
				[ 1103.095, -309.4501, 781.1109 ]
			],
			[
				9,
				270.0,
				0.0,
				0.1,
				[ 1087.641, -309.5976, 780.9481 ]
			],
			[
				9,
				270.0,
				0.0,
				0.7002658,
				[ 1094.265, -308.3763, 765.497 ]
			],
			[
				9,
				270.0,
				0.0,
				0.7002658,
				[ 1095.184, -308.8291, 737.8161 ]
			],
			[
				11,
				270.0,
				63.0,
				0.3669466,
				[ 1077.501, 182.9235, 771.834 ]
			],
			[
				11,
				270.0,
				63.0,
				0.3669466,
				[ 1078.703, 182.9389, 753.551 ]
			],
			[
				11,
				270.0,
				63.0,
				0.3669466,
				[ 1079.621, 182.9497, 736.3304 ]
			],
			[
				11,
				90.0,
				0.0,
				0.3926677,
				[ 1095.034, -303.7853, 736.6428 ]
			],
			[
				11,
				90.0,
				0.0,
				0.3926677,
				[ 1094.38, -303.7555, 754.0218 ]
			],
			[
				11,
				90.0,
				0.0,
				0.3926677,
				[ 1094.228, -303.7742, 772.1801 ]
			],
			[
				11,
				90.0,
				63.0,
				0.3926677,
				[ 1109.785, 183.4871, 772.4786 ]
			],
			[
				11,
				90.0,
				63.0,
				0.3926677,
				[ 1110.037, 183.486, 754.343 ]
			],
			[
				11,
				90.0,
				63.0,
				0.3926677,
				[ 1110.332, 183.4859, 737.2457 ]
			],
			[
				11,
				90.0,
				0.0,
				0.3926677,
				[ 1095.01, 197.9512, 736.7269 ]
			],
			[
				11,
				90.0,
				0.0,
				0.3926677,
				[ 1094.669, 197.9073, 753.7628 ]
			],
			[
				11,
				90.0,
				0.0,
				0.3926677,
				[ 1093.659, -301.9546, 771.8295 ]
			],
			[
				11,
				90.0,
				0.0,
				0.3926677,
				[ 1093.659, 197.9363, 771.8295 ]
			],
			[
				9,
				90.0,
				63.0,
				0.5393898,
				[ 1112.691, -316.4649, 763.2911 ]
			],
			[
				9,
				90.0,
				63.0,
				0.5393898,
				[ 1107.712, -306.3373, 763.12 ]
			],
			[
				9,
				90.0,
				63.0,
				0.5393898,
				[ 1108.568, -306.4309, 726.2015 ]
			],
			[
				9,
				90.0,
				63.0,
				0.5393898,
				[ 1108.568, 193.3208, 726.2015 ]
			],
			[
				9,
				270.0,
				63.0,
				0.5393898,
				[ 1082.41, 193.7915, 725.4556 ]
			],
			[
				0,
				270.0,
				0.0,
				1.645104,
				[ 1071.407, 182.7807, 729.5709 ]
			],
			[
				0,
				270.0,
				0.0,
				1.645104,
				[ 1117.493, 183.5854, 730.6777 ]
			],
			[
				9,
				270.0,
				0.0,
				0.8215816,
				[ 1094.741, -299.011, 723.6147 ]
			],
			[
				9,
				270.0,
				0.0,
				0.8215816,
				[ 1094.741, -299.3524, 723.6147 ]
			],
			[
				9,
				270.0,
				0.0,
				0.8215816,
				[ 1094.741, 200.6849, 723.6147 ]
			]
		],
		"players" : 
		[
			{
				"armor" : 
				{
					"head" : 2.25,
					"high" : 2.25,
					"low" : 2.25
				},
				"clothes" : 
				[
					{
						"path" : "Textures/GiTop.png",
						"tintb" : 1.0,
						"tintg" : 1.0,
						"tintr" : 1.0
					},
					{
						"path" : "Textures/ClFeng.png",
						"tintb" : 1.0,
						"tintg" : 1.0,
						"tintr" : 1.0
					},
					{
						"path" : "Textures/GiBottom.png",
						"tintb" : 0.05,
						"tintg" : 0.05,
						"tintr" : 0.05
					}
				],
				"coords" : [ 1096.242, 186.2029, 692.6725 ],
				"creature" : 0,
				"metal" : 
				{
					"head" : false,
					"high" : false,
					"low" : false
				},
				"power" : 1.111111,
				"protection" : 
				{
					"head" : 1.0,
					"high" : 1.0,
					"low" : 1.0
				},
				"speedmult" : 1.0,
				"targetyaw" : 7557.529,
				"weapons" : [ 2 ],
				"whichskin" : 0,
				"yaw" : 7557.529
			},
			{
				"armor" : 
				{
					"head" : 1.0,
					"high" : 1.0,
					"low" : 1.0
				},
				"coords" : [ 1094.355, 186.2196, 778.1125 ],
				"creature" : 1,
				"howactive" : 0,
				"immobile" : false,
				"metal" : 
				{
					"head" : false,
					"high" : false,
					"low" : false
				},
				"power" : 1.05,
				"proportions" : [ 1.02, 1.03, 1.04, 1.03 ],
				"protection" : 
				{
					"head" : 1.0,
					"high" : 1.0,
					"low" : 1.0
				},
				"scale" : 0.2346,
				"speedmult" : 1.03,
				"waypoint" : 0,
				"whichskin" : 1,
				"yaw" : -4137.602
			},
			{
				"armor" : 
				{
					"head" : 1.0,
					"high" : 1.0,
					"low" : 1.0
				},
				"coords" : [ 1092.64, 186.1895, 777.7524 ],
				"creature" : 1,
				"howactive" : 0,
				"immobile" : false,
				"metal" : 
				{
					"head" : false,
					"high" : false,
					"low" : false
				},
				"power" : 1.05,
				"proportions" : [ 1.02, 1.03, 1.04, 1.03 ],
				"protection" : 
				{
					"head" : 1.0,
					"high" : 1.0,
					"low" : 1.0
				},
				"scale" : 0.2346,
				"speedmult" : 1.03,
				"waypoint" : 0,
				"whichskin" : 1,
				"yaw" : -3781.999
			},
			{
				"armor" : 
				{
					"head" : 1.0,
					"high" : 1.7,
					"low" : 1.4
				},
				"clothes" : 
				[
					{
						"path" : "Textures/Pants.png",
						"tintb" : 0.2,
						"tintg" : 0.2,
						"tintr" : 0.2
					},
					{
						"path" : "Textures/LeatherArmor.png",
						"tintb" : 0.8,
						"tintg" : 0.8,
						"tintr" : 0.6
					},
					{
						"path" : "Textures/LeatherWristLeft.png",
						"tintb" : 1.0,
						"tintg" : 1.0,
						"tintr" : 1.0
					},
					{
						"path" : "Textures/LeatherWristRight.png",
						"tintb" : 1.0,
						"tintg" : 1.0,
						"tintr" : 1.0
					}
				],
				"coords" : [ 1093.596, 186.2064, 778.3023 ],
				"creature" : 0,
				"howactive" : 0,
				"immobile" : false,
				"metal" : 
				{
					"head" : false,
					"high" : true,
					"low" : false
				},
				"power" : 1.05,
				"proportions" : [ 1.0, 0.9999999, 1.0, 1.0 ],
				"protection" : 
				{
					"head" : 1.0,
					"high" : 1.4,
					"low" : 1.2
				},
				"scale" : 0.2,
				"speedmult" : 1.04,
				"waypoint" : 0,
				"weapons" : [ 2 ],
				"whichskin" : 7,
				"yaw" : -3779.192
			}
		],
		"radius" : 158.1887,
		"skybox" : 
		{
			"b" : 0.9,
			"g" : 0.9,
			"lightb" : 0.9,
			"lightg" : 0.9,
			"lightr" : 0.9,
			"r" : 0.9,
			"texture" : true
		},
		"type" : 0,
		"viewdistance" : 100.0
	},
	"version" : 13
}