{
    "version": 5,
    "name": "timespinner.zip",
    "items": [
        "timespinner/",
        "Timespinner.sh"
    ],
    "items_opt": [],
    "attr": {
        "title": "Timespinner",
        "porter": [
            "Johnny on Flame"
        ],
        "desc": "Travel back in time to change fate itself, in this beautifully crafted story-driven adventure, inspired by classic 90s action-platformers.",
        "desc_md": null,
        "inst": "You must have a copy of Timespinner for Linux copied to the ports/timespinner/gamedata folder.",
        "inst_md": null,
        "genres": [
            "action",
            "adventure",
            "rpg",
            "platformer"
        ],
        "image": null,
        "rtr": false,
        "exp": false,
        "runtime": ["mono-6.12.0.122-aarch64.squashfs"],
        "store": [
            {
                "name": "Steam",
                "url": "https://store.steampowered.com/app/368620/"
            }
        ],
        "availability": "paid",
        "reqs": [],
        "arch": [],
        "igdb_id": 28952,
        "steam_id": 368620
    }
}