{
  "version": 2,
  "name": "sonictt16b.zip",
  "items": [
    "Sonic Triple Trouble - 16-Bit.sh",
    "sonictt16b/"
  ],
  "items_opt": [],
  "attr": {
    "title": "Sonic Triple Trouble - 16-Bit",
    "porter": [
      "Jeod",
	  "JanTrueno"
    ],
    "desc": "What if Sonic Triple Trouble had been originally released on the Sega Genesis / MegaDrive, after Sonic 3 & Knuckles?",
    "inst": "Download the 32-bit or 64-bit android apk from Gamejolt and put it in `ports/sonictt16b`.",
    "genres": [
      "action",
      "adventure",
      "arcade",
      "platformer"
    ],
    "image": "screenshot.png",
    "rtr": false,
    "exp": false,
    "runtime": null,
    "reqs": ["!arkos"],
    "arch": ["aarch64"]
  }
}