{
    "version": 2,
    "name": "skijump3.zip",
    "items": [
        "skijump3/",
        "Skijump3.sh"
    ],
    "items_opt": null,
    "attr": {
        "title": "SkiJump3",
        "desc": "Ski Jump International v3",
        "inst": "Ready to run.",
        "genres": [
            "sports"
        ],
        "porter": [
            "Cebion"
        ],
        "image": {},
        "rtr": true,
        "runtime": null,
        "reqs": [],
        "arch": [
            "aarch64"
        ]
    }
}