{
  "version": 5,
  "name": "powder.zip",
  "items": [
    "Powder.sh",
    "powder/"
  ],
  "items_opt": [],
  "attr": {
    "title": "Powder",
    "porter": [
      "Cebion"
    ],
    "desc": "A roguelike is a dungeon crawler where no two games are the same. The maps are different, the items are different, there are no guaranteed win paths.",
    "desc_md": null,
    "inst": "Powder files are already included and ready to go.",
    "inst_md": null,
    "genres": [
      "rpg",
      "roguelike"
    ],
    "image": null,
    "rtr": true,
    "exp": false,
    "runtime": null,
    "availability": "full",
    "reqs": [],
    "arch": [
      "aarch64"
    ],
    "min_glibc": "",
    "igdb_id": 49505
  }
}
