<?xml version="1.0"?>
<!-- Generated with script from SVN rev 17016 -->
<graph>
  <!-- First define all nodes of the graph, and what quads they represent -->
  <node-list from-quad="0" to-quad="289"/>  <!-- map each quad to a node  -->
  <!-- Define the main loop -->
  <edge-loop from="0" to="210"/>
  <!-- Shortcut add driveline 4 -->
  <edge from="103" to="211"/>
  <edge-line from="211" to="234"/>
  <edge from="234" to="125"/>
  <!-- Shortcut add driveline 2 -->
  <edge from="112" to="235"/>
  <edge-line from="235" to="244"/>
  <edge from="244" to="225"/>
  <!-- Shortcut add driveline 3 -->
  <edge from="20" to="245"/>
  <edge-line from="245" to="277"/>
  <edge from="277" to="50"/>
  <!-- Shortcut add driveline 1 -->
  <edge from="182" to="278"/>
  <edge-line from="278" to="289"/>
  <edge from="289" to="195"/>
</graph>
