<?xml version="1.0" encoding="utf-8"?>
<gameList>
  <game>
    <path>./Habroxia.sh</path>
    <name>Habroxia</name>
    <desc>Blast your way through a myriad of extra-terrestrial incursions in this arcade-style scrolling shooter! Pilot the ship Habroxia through 15 levels featuring intense boss fights, rescue missions, shifting perspectives, and untold surprises.</desc>
    <releasedate>20201201T000000</releasedate>
    <developer>Lillymo Games</developer>
    <publisher>Lillymo Games</publisher>
    <genre>Action</genre>
    <image>./habroxia/screenshot.png</image>
  </game>
</gameList>