<?xml version="1.0"?>
<level world="resources/level-planet/world.svg" music="resources/music/planet.ogg">
    <camera type="followcamera" filename="resources/player/camera.xml" />
    <entity id="player" filename="resources/player/player.xml">
        <position x="200" y="20" />
    </entity>
    <entity id="obtain-hat" filename="resources/hat/obtain-hat.xml">
        <position x="3700" y="160" />
    </entity>
    <entity id="velociraptor-01" filename="resources/velociraptor/velociraptor.xml">
        <position x="2100" y="40" />
    </entity>
    <entity id="hedgehog-01" filename="resources/hedgehog/hedgehog.xml">
        <position x="3316" y="40" />
        <controller type="patrollingcontroller" x1="3290" x2="3700" />
    </entity>
    <entity id="plant-01" filename="resources/plant/plant.xml">
        <position x="1113" y="250" />
        <controller type="simplebirdcontroller">
            <point x="1113" y="250" />
            <point x="1113" y="382" />
        </controller>
    </entity>
    <entity id="plant-02" filename="resources/plant/plant.xml">
        <position x="2681" y="793" />
        <controller type="simplebirdcontroller">
            <point x="2681" y="793" />
            <point x="2681" y="670" />
        </controller>
    </entity>
    <entity id="plant-03" filename="resources/plant/plant.xml">
        <position x="2100" y="740" />
        <controller type="simplebirdcontroller">
            <point x="2100" y="740" />
            <point x="2243" y="650" />
        </controller>
    </entity>
    <entity id="star" script="resources/level-planet/star.lua">
        <position x="1564" y="490" />
        <radius x="70" y="70" />
    </entity>
</level>
