<?xml version="1.0" encoding="utf-8"?>
<gameList>
  <game>
    <path>./Godstone.sh</path>
    <name>Godstone</name>
    <desc>Wield magic and weaponry in this roguelike dungeoncrawler, forge powerful builds and explore a story that evolves based on your actions. The end goal: Claim the Godstone before those who would use it to destroy your kind. </desc>
    <releasedate>20250330T000000</releasedate>
    <developer>Demented Plant</developer>
    <publisher>Demented Plant</publisher>
    <genre>Action Adventure</genre>
    <image>./godstone/cover.png</image>
  </game>
</gameList>