{
  "version": 3,
  "name": "passage.zip",
  "items": [
    "Passage.sh",
    "passage"
  ],
  "items_opt": [],
  "attr": {
    "title": "Passage",
    "porter": [
      "Cebion"
    ],
    "desc": "Passage is a five-minute experimental art game that metaphorically represents an entire human lifetime, allowing players to navigate a pixelated world while exploring themes of love, aging, and mortality.\n\nThe game only lasts 5 minutes. If you don't get the point at first, please keep playing.",
    "desc_md": null,
    "inst": "Ready to run!",
    "inst_md": null,
    "genres": [
      "other"
    ],
    "image": null,
    "rtr": true,
    "exp": false,
    "runtime": null,
    "reqs": [],
    "arch": [
      "aarch64"
    ]
  }
}